data/tutorials/chatbot-simulation-evaluation/simulation_utils.py
data/tutorials/llm-compiler/math_tools.py
data/tutorials/llm-compiler/output_parser.py
docs/Makefile
docs/make.bat
docs/_build/html/_static/file.png
docs/_build/html/_static/minus.png
docs/_build/html/_static/plus.png
docs/source/authors.rst
docs/source/conf.py
docs/source/contributing.rst
docs/source/history.rst
docs/source/index.rst
docs/source/installation.rst
docs/source/langflow_chat.rst
docs/source/quick_pp.lithology.rst
docs/source/quick_pp.machine_learning.rst
docs/source/quick_pp.plotter.rst
docs/source/quick_pp.rock_physics.rst
docs/source/quick_pp.rst
docs/source/usage.rst
docs/static/quick_pp_demo.gif
notebooks/data/01_raw/VOLVE/seismic/examples/QuickOverview.py
notebooks/data/01_raw/VOLVE/seismic/examples/example_amplitude_extraction_displays.py
notebooks/data/01_raw/VOLVE/seismic/examples/example_depth_conversion.py
notebooks/data/01_raw/VOLVE/seismic/examples/example_extract_arbitrary_line.py
notebooks/data/01_raw/VOLVE/seismic/examples/example_extract_data_on_a_horizon.py
notebooks/data/01_raw/VOLVE/seismic/examples/example_merge_surveys.py
notebooks/data/01_raw/VOLVE/seismic/examples/example_segy_headers.py
notebooks/data/01_raw/VOLVE/seismic/examples/example_segysak_basics.py
notebooks/data/01_raw/VOLVE/seismic/examples/example_segysak_dask.py
notebooks/data/01_raw/VOLVE/seismic/examples/example_segysak_segy_vectorisation.py
notebooks/data/01_raw/VOLVE/seismic/examples/example_working_with_3d_gathers.py
notebooks/data/01_raw/VOLVE/seismic/examples/archive/ar.examples_subsurface.py
notebooks/data/01_raw/VOLVE/seismic/examples/archive/example_zgy.py
quick_pp/__init__.py
quick_pp/cli.py
quick_pp/config.py
quick_pp/core_analysis.py
quick_pp/fluid_type.py
quick_pp/las_handler.py
quick_pp/permeability.py
quick_pp/porosity.py
quick_pp/qaqc.py
quick_pp/ressum.py
quick_pp/rock_type.py
quick_pp/saturation.py
quick_pp/utils.py
quick_pp/app/backend/__init__.py
quick_pp/app/backend/exceptions.py
quick_pp-0.2.106.dist-info/licenses/LICENSE
quick_pp-0.2.106.dist-info/METADATA
quick_pp-0.2.106.dist-info/WHEEL
quick_pp-0.2.106.dist-info/entry_points.txt
quick_pp-0.2.106.dist-info/top_level.txt
quick_pp-0.2.106.dist-info/RECORD
