Metadata-Version: 2.4
Name: quick-pp
Version: 0.2.106
Summary: Python package to assist in providing quick-look preliminary petrophysical estimation.
Author-email: Imran Fadhil <imranfadhil@gmail.com>
Maintainer-email: Imran Fadhil <imranfadhil@gmail.com>
License-Expression: MIT
Project-URL: Homepage, https://github.com/imranfadhil/quick_pp
Project-URL: Repository, https://github.com/imranfadhil/quick_pp
Project-URL: Documentation, https://quick-pp.readthedocs.io
Project-URL: Bug Reports, https://github.com/imranfadhil/quick_pp/issues
Project-URL: Changelog, https://github.com/imranfadhil/quick_pp/blob/main/CHANGELOG.md
Keywords: geoscience,petrophysics,well log,well plot,quick_pp,multi mineral,rock typing,saturation height function,shf
Classifier: Development Status :: 2 - Pre-Alpha
Classifier: Intended Audience :: Developers
Classifier: Intended Audience :: Science/Research
Classifier: Intended Audience :: Education
Classifier: Natural Language :: English
Classifier: Operating System :: OS Independent
Classifier: Programming Language :: Python :: 3.11
Classifier: Programming Language :: Python :: 3.12
Classifier: Topic :: Scientific/Engineering
Classifier: Topic :: Scientific/Engineering :: Physics
Classifier: Topic :: Scientific/Engineering :: Visualization
Classifier: Topic :: Software Development :: Libraries :: Python Modules
Requires-Python: >=3.11
License-File: LICENSE
Requires-Dist: celery
Requires-Dist: Click>=7.0
Requires-Dist: fastapi
Requires-Dist: jinja2
Requires-Dist: lasio
Requires-Dist: loguru
Requires-Dist: matplotlib==3.8.0
Requires-Dist: orjson
Requires-Dist: pandas
Requires-Dist: plotly
Requires-Dist: psycopg2-binary
Requires-Dist: pydantic
Requires-Dist: pydantic_core
Requires-Dist: python-dotenv
Requires-Dist: python-multipart
Requires-Dist: redis
Requires-Dist: requests
Requires-Dist: ruptures
Requires-Dist: setuptools<81
Requires-Dist: sqlalchemy
Requires-Dist: uvicorn
Requires-Dist: wellpathpy
Requires-Dist: welly
Provides-Extra: dev
Requires-Dist: black>=23.0; extra == "dev"
Requires-Dist: build>=0.10; extra == "dev"
Requires-Dist: dtw-python; extra == "dev"
Requires-Dist: fastapi-mcp; extra == "dev"
Requires-Dist: mlflow; extra == "dev"
Requires-Dist: mypy>=1.5; extra == "dev"
Requires-Dist: pre-commit>=3.0; extra == "dev"
Requires-Dist: ptitprince; extra == "dev"
Requires-Dist: pytest>=7.0; extra == "dev"
Requires-Dist: pytest-cov>=4.0; extra == "dev"
Requires-Dist: pytest-mock>=3.10; extra == "dev"
Requires-Dist: ruff>=0.1.0; extra == "dev"
Requires-Dist: SALib==1.5.1; extra == "dev"
Requires-Dist: scikit-learn; extra == "dev"
Requires-Dist: twine>=4.0; extra == "dev"
Provides-Extra: test
Requires-Dist: pytest>=7.0; extra == "test"
Requires-Dist: pytest-cov>=4.0; extra == "test"
Requires-Dist: pytest-mock>=3.10; extra == "test"
Requires-Dist: pytest-xdist>=3.0; extra == "test"
Provides-Extra: docs
Requires-Dist: sphinx>=7.0; extra == "docs"
Requires-Dist: sphinx-rtd-theme>=1.3; extra == "docs"
Requires-Dist: sphinx-autodoc-typehints>=1.24; extra == "docs"
Requires-Dist: myst-parser>=2.0; extra == "docs"
Provides-Extra: full
Requires-Dist: jupyter>=1.0; extra == "full"
Requires-Dist: ipykernel>=6.0; extra == "full"
Requires-Dist: seaborn>=0.12; extra == "full"
Requires-Dist: bokeh>=3.0; extra == "full"
Dynamic: license-file
